path_chronicle/__init__.py
path_chronicle/config.py
path_chronicle/fso_expansion.py
path_chronicle/generate_paths.py
path_chronicle/interface.py
path_chronicle/schema.py
path_chronicle/utils.py
path_chronicle-0.1.7.dist-info/LICENSE
path_chronicle-0.1.7.dist-info/METADATA
path_chronicle-0.1.7.dist-info/WHEEL
path_chronicle-0.1.7.dist-info/entry_points.txt
path_chronicle-0.1.7.dist-info/RECORD
